MANIFEST.in
README
setup.py
bin/versioner-cli
config/versioner
lib/versioner_cli/__init__.py
lib/versioner_cli.egg-info/PKG-INFO
lib/versioner_cli.egg-info/SOURCES.txt
lib/versioner_cli.egg-info/dependency_links.txt
lib/versioner_cli.egg-info/requires.txt
lib/versioner_cli.egg-info/top_level.txt
lib/versioner_cli/api/__init__.py
lib/versioner_cli/api/enums.py
lib/versioner_cli/cli/__init__.py
lib/versioner_cli/cli/config.py
lib/versioner_cli/cli/enums.py
lib/versioner_cli/cli/exceptions.py
lib/versioner_cli/cli/tasks.py