Metadata-Version: 1.0
Name: versioner-cli
Version: 1.0.27
Summary: cli tool to interact with versioner service
Home-page: https://github.com/bookmd/bookmd-versioner-cli
Author: Ben Waters
Author-email: ben@book-md.com
License: MIT
Platform: UNKNOWN
